{"estate-price": ["\u00e2\u201a\u00ac 115.000", "\u00e2\u201a\u00ac 395.000", "\u00e2\u201a\u00ac 135.000", "\u00e2\u201a\u00ac 115.000", "\u00e2\u201a\u00ac 395.000", "\u00e2\u201a\u00ac 135.000", "\u00e2\u201a\u00ac 115.000", "\u00e2\u201a\u00ac 395.000", "\u00e2\u201a\u00ac 135.000", "\u00e2\u201a\u00ac 115.000", "\u00e2\u201a\u00ac 395.000", "\u00e2\u201a\u00ac 135.000", "\u00e2\u201a\u00ac 115.000", "\u00e2\u201a\u00ac 395.000", "\u00e2\u201a\u00ac 135.000", "\u00e2\u201a\u00ac 115.000", "\u00e2\u201a\u00ac 395.000", "\u00e2\u201a\u00ac 135.000", "\u00e2\u201a\u00ac 115.000", "\u00e2\u201a\u00ac 395.000", "\u00e2\u201a\u00ac 135.000", "\u00e2\u201a\u00ac 115.000", "\u00e2\u201a\u00ac 115.000", "\u00e2\u201a\u00ac 395.000", "\u00e2\u201a\u00ac 395.000", "\u00e2\u201a\u00ac 135.000", "\u00e2\u201a\u00ac 135.000"], "estate-title": ["Trilocale in vendita", "Bifamiliare in vendita", "Trilocale in vendita", "Trilocale in vendita", "Bifamiliare in vendita", "Trilocale in vendita", "Trilocale in vendita", "Bifamiliare in vendita", "Trilocale in vendita", "Trilocale in vendita", "Bifamiliare in vendita", "Trilocale in vendita", "Trilocale in vendita", "Bifamiliare in vendita", "Trilocale in vendita", "Trilocale in vendita", "Bifamiliare in vendita", "Trilocale in vendita", "Trilocale in vendita", "Bifamiliare in vendita", "Trilocale in vendita", "Trilocale in vendita", "Trilocale in vendita", "Bifamiliare in vendita", "Bifamiliare in vendita", "Trilocale in vendita", "Trilocale in vendita"], "estate-subtitle": ["Inveruno, Via Raffaello Sanzio", "Inveruno, Via Benedetto Croce", "Inveruno, Via Milano - Furato", "Inveruno, Via Raffaello Sanzio", "Inveruno, Via Benedetto Croce", "Inveruno, Via Milano - Furato", "Inveruno, Via Raffaello Sanzio", "Inveruno, Via Benedetto Croce", "Inveruno, Via Milano - Furato", "Inveruno, Via Raffaello Sanzio", "Inveruno, Via Benedetto Croce", "Inveruno, Via Milano - Furato", "Inveruno, Via Raffaello Sanzio", "Inveruno, Via Benedetto Croce", "Inveruno, Via Milano - Furato", "Inveruno, Via Raffaello Sanzio", "Inveruno, Via Benedetto Croce", "Inveruno, Via Milano - Furato", "Inveruno, Via Raffaello Sanzio", "Inveruno, Via Benedetto Croce", "Inveruno, Via Milano - Furato", "Inveruno, Via Raffaello Sanzio", "Inveruno, Via Raffaello Sanzio", "Inveruno, Via Benedetto Croce", "Inveruno, Via Benedetto Croce", "Inveruno, Via Milano - Furato", "Inveruno, Via Milano - Furato"], "estate-rooms": ["3 locali", "4 locali", "3 locali", "3 locali", "4 locali", "3 locali", "3 locali", "4 locali", "3 locali", "3 locali", "4 locali", "3 locali", "3 locali", "4 locali", "3 locali", "3 locali", "4 locali", "3 locali", "3 locali", "4 locali", "3 locali", "3 locali", "3 locali", "4 locali", "4 locali", "3 locali", "3 locali"], "estate-surface": ["89 Mq", "277 Mq", "107 Mq", "89 Mq", "277 Mq", "107 Mq", "89 Mq", "277 Mq", "107 Mq", "89 Mq", "277 Mq", "107 Mq", "89 Mq", "277 Mq", "107 Mq", "89 Mq", "277 Mq", "107 Mq", "89 Mq", "277 Mq", "107 Mq", "89 Mq", "89 Mq", "277 Mq", "277 Mq", "107 Mq", "107 Mq"]}